siatune/__init__.py
siatune/__main__.py
siatune/run.py
siatune/version.py
siatune/apis/__init__.py
siatune/apis/analysis.py
siatune/codebase/__init__.py
siatune/codebase/base.py
siatune/codebase/blackbox.py
siatune/codebase/builder.py
siatune/codebase/cont_test_func.py
siatune/codebase/disc_test_func.py
siatune/codebase/mim.py
siatune/codebase/mm.py
siatune/codebase/mmcls.py
siatune/codebase/mmdet.py
siatune/codebase/mmedit.py
siatune/codebase/mmseg.py
siatune/core/__init__.py
siatune/core/context.py
siatune/core/launch.py
siatune/core/hooks/__init__.py
siatune/core/hooks/reporter.py
siatune/core/rewriters/__init__.py
siatune/core/rewriters/base.py
siatune/core/rewriters/builder.py
siatune/core/rewriters/dump.py
siatune/core/rewriters/instantiate.py
siatune/core/rewriters/merge.py
siatune/core/rewriters/patch.py
siatune/core/rewriters/path.py
siatune/core/rewriters/register.py
siatune/core/rewriters/resume.py
siatune/tune/__init__.py
siatune/tune/config.py
siatune/tune/tuner.py
siatune/tune/callbacks/__init__.py
siatune/tune/callbacks/builder.py
siatune/tune/callbacks/mlflow.py
siatune/tune/schedulers/__init__.py
siatune/tune/schedulers/builder.py
siatune/tune/schedulers/pbt.py
siatune/tune/searchers/__init__.py
siatune/tune/searchers/builder.py
siatune/tune/searchers/nevergrad.py
siatune/tune/spaces/__init__.py
siatune/tune/spaces/base.py
siatune/tune/spaces/builder.py
siatune/tune/spaces/choice.py
siatune/tune/spaces/grid_search.py
siatune/tune/spaces/sample_from.py
siatune/tune/stoppers/__init__.py
siatune/tune/stoppers/builder.py
siatune/tune/stoppers/dict_stop.py
siatune/tune/stoppers/early_drop.py
siatune/tune/utils/__init__.py
siatune/tune/utils/name_creator.py
siatune/utils/__init__.py
siatune/utils/args.py
siatune/utils/config.py
siatune/utils/container.py
siatune/utils/dist.py
siatune/utils/logger.py
siatune/utils/mim.py
siatune/utils/setup_env.py
siatune-0.4.0rc1.dist-info/LICENSE
siatune-0.4.0rc1.dist-info/METADATA
siatune-0.4.0rc1.dist-info/WHEEL
siatune-0.4.0rc1.dist-info/top_level.txt
siatune-0.4.0rc1.dist-info/RECORD
