Metadata-Version: 2.1
Name: siatune
Version: 0.4.0rc1
Summary: UNKNOWN
Home-page: UNKNOWN
Author: SIA
License: UNKNOWN
Platform: UNKNOWN
Requires-Dist: mmengine
Requires-Dist: openmim
Requires-Dist: ray[data] (==2.2.0)
Requires-Dist: ray[tune] (==2.2.0)
Provides-Extra: optional
Requires-Dist: bayesian-optimization (==1.2.0) ; extra == 'optional'
Requires-Dist: ConfigSpace ; extra == 'optional'
Requires-Dist: flaml (==1.0.14) ; extra == 'optional'
Requires-Dist: hpbandster ; extra == 'optional'
Requires-Dist: hyperopt (==0.2.5) ; extra == 'optional'
Requires-Dist: mlflow (==1.23.1) ; extra == 'optional'
Requires-Dist: nevergrad (==0.4.3.post7) ; extra == 'optional'
Requires-Dist: optuna (==2.10.0) ; extra == 'optional'
Requires-Dist: scikit-learn ; extra == 'optional'
Requires-Dist: scikit-optimize (==0.9.0) ; extra == 'optional'
